document_mover-0.3.7.dist-info/METADATA
document_mover-0.3.7.dist-info/WHEEL
document_mover-0.3.7.dist-info/entry_points.txt
document_mover/__init__.py
document_mover/document_mover.py
document_mover/file_list.py
document_mover/file_lock.py
document_mover/pdf_merger.py
document_mover/py.typed
document_mover-0.3.7.dist-info/RECORD
