Metadata-Version: 2.1
Name: document-mover
Version: 0.3.7
Summary: document mover, for moving scans stable and merge pdfs
Author-Email: sebgad <sebgad@sebgad.com>
License: MIT
Classifier: Development Status :: 3 - Alpha
Classifier: Intended Audience :: Developers
Classifier: License :: OSI Approved :: MIT License
Classifier: Programming Language :: Python :: 3
Classifier: Programming Language :: Python :: 3.12
Classifier: Programming Language :: Python :: 3.13
Requires-Python: >=3.12
Requires-Dist: ruff>=0.14.8
Requires-Dist: pypdf>=6.4.1
Requires-Dist: mypy>=1.19.0
Requires-Dist: pytest>=9.0.2
Requires-Dist: pytest-cov>=7.0.0
